projectframe/__init__.py
projectframe/core/__init__.py
projectframe/core/core.py
projectframe/engines/__init__.py
projectframe/engines/pandas_engine.py
projectframe/engines/pandas_h5.py
projectframe/objects/__init__.py
projectframe/objects/frame.py
projectframe/objects/multiframe.py
projectframe/objects/obsframe.py
projectframe/objects/unstructured.py
projectframe-1.0.6.dist-info/LICENSE.md
projectframe-1.0.6.dist-info/METADATA
projectframe-1.0.6.dist-info/WHEEL
projectframe-1.0.6.dist-info/RECORD
